midgard/__init__.py
midgard/collections/__init__.py
midgard/collections/enums.py
midgard/collections/plate_motion_models.py
midgard/config/__init__.py
midgard/config/config.py
midgard/config/files.py
midgard/data/__init__.py
midgard/data/_h5utils.py
midgard/data/_position.py
midgard/data/_taiutc.txt
midgard/data/_time.py
midgard/data/collection.py
midgard/data/dataset.py
midgard/data/position.py
midgard/data/sigma.py
midgard/data/time.py
midgard/data/fieldtypes/__init__.py
midgard/data/fieldtypes/_fieldtype.py
midgard/data/fieldtypes/bool.py
midgard/data/fieldtypes/collection.py
midgard/data/fieldtypes/float.py
midgard/data/fieldtypes/position.py
midgard/data/fieldtypes/position_delta.py
midgard/data/fieldtypes/posvel.py
midgard/data/fieldtypes/posvel_delta.py
midgard/data/fieldtypes/sigma.py
midgard/data/fieldtypes/text.py
midgard/data/fieldtypes/time.py
midgard/data/fieldtypes/time_delta.py
midgard/dev/__init__.py
midgard/dev/console.py
midgard/dev/exceptions.py
midgard/dev/library.py
midgard/dev/log.py
midgard/dev/plugins.py
midgard/dev/profiler.py
midgard/dev/timer.py
midgard/dev/util.py
midgard/files/__init__.py
midgard/files/dates.py
midgard/files/dependencies.py
midgard/files/files.py
midgard/files/url.py
midgard/gnss/__init__.py
midgard/gnss/antenna_calibration.py
midgard/gnss/compute_dops.py
midgard/gnss/gnss.py
midgard/gnss/klobuchar.py
midgard/gnss/solution_validation.py
midgard/math/__init__.py
midgard/math/constant.py
midgard/math/constant.txt
midgard/math/ellipsoid.py
midgard/math/interpolation.py
midgard/math/linear_regression.py
midgard/math/nputil.py
midgard/math/planetary_motion.py
midgard/math/plate_motion.py
midgard/math/rotation.py
midgard/math/spatial_interpolation.py
midgard/math/transformation.py
midgard/math/unit.py
midgard/math/unit.txt
midgard/parsers/__init__.py
midgard/parsers/_parser.py
midgard/parsers/_parser_chain.py
midgard/parsers/_parser_line.py
midgard/parsers/_parser_rinex.py
midgard/parsers/_parser_sinex.py
midgard-1.3.0.dist-info/LICENSE
midgard-1.3.0.dist-info/WHEEL
midgard-1.3.0.dist-info/METADATA
midgard-1.3.0.dist-info/RECORD
