Metadata-Version: 2.1
Name: midgard
Version: 1.3.0
Summary: Midgard, the Python Geodesy library
Home-page: https://github.com/kartverket/midgard
Keywords: geodesy utilities
Author: Norwegian Mapping Authority
Author-email: geir.arne.hjelle@kartverket.no
Classifier: Development Status :: 2 - Pre-Alpha
Classifier: Intended Audience :: Developers
Classifier: Intended Audience :: Science/Research
Classifier: License :: OSI Approved :: MIT License
Classifier: Natural Language :: English
Classifier: Operating System :: MacOS
Classifier: Operating System :: Microsoft
Classifier: Operating System :: POSIX :: Linux
Classifier: Programming Language :: Python :: 3.9
Classifier: Topic :: Scientific/Engineering
Classifier: Topic :: Software Development :: Libraries :: Python Modules
